<liste_avis>
<avis>
<auteur>François</auteur>
<note>3</note>
<point_positif>bonne souplesse et confort du silicone</point_positif>
<point_negatif>9 fois sur 10 la sangle se dérègle avant la plongé</point_negatif>
<date>01/01/2013</date>
<commentaire>le système de verrouillage de la sangle est tout à fait inefficace tant que le masque n'est pas sur le visage.<br/>ce qui oblige à re-règler le masque quasiment à chaque fois.</commentaire>
</avis>
<avis>
<auteur>Marc</auteur>
<note>4</note>
<point_positif>Faible encombrement, longévité de la jupe</point_positif>
<point_negatif>Boucles en plastique</point_negatif>
<date>23/12/2012</date>
<commentaire>Mon premier masque (il y a 10 ans) :) Un produit intéressant mais deux points à sérieusement prendre en compte :<br/>- masque pour les visages fins (bien pour les enfants) : sinon pas adapté du tout<br/>- boucles en plastique (qui permettent d'accrocher la sangle) cassable et (presque) introuvable : c'est cheap par rapport aux concurrents<br/><br/>Aujourd'hui, 'ai grandi, j'ai un Mares avec des boucles plus solides (mais à 40 euros...). En synthèse, un bon modèle pour commencer en occasionnel</commentaire>
</avis>
<avis>
<auteur>Marc</auteur>
<note>1</note>
<point_positif>Design</point_positif>
<point_negatif>Buée - pas étanche - attache mauvaise qualite</point_negatif>
<date>05/06/2012</date>
<commentaire>J'ai utilisé ce masque 2 fois et j'en suis très déçu. L'eau rentre rapidement à l'intérieur et quand on essaye de mieux serrer les attaches celles ci se détendent automatiquement... Ne parlons pas de la buée toutes les 30 secondes il faut nettoyer le verre. Bref je suis déçu et je ne le recommande pas même à ce niveau de prix.</commentaire>
</avis>
<avis>
<auteur>Lorane</auteur>
<note>4</note>
<point_positif>esthétique, pas de buée</point_positif>
<point_negatif>système de réglage fragile</point_negatif>
<date>07/05/2012</date>
<commentaire>le masque se dérègle trop facilement.<br/></commentaire>
</avis>
<avis>
<auteur>m</auteur>
<note>3</note>
<point_positif>Bonne visibilité et confort.</point_positif>
<point_negatif>Système de serrage fragile !</point_negatif>
<date>04/10/2011</date>
<commentaire>Très bonne visibilité. Absence de condensation dans les verres. Absence de fuite. Confortable sur le visage. Mais système de serrage fragile ! Il a sufis que je serre un peut fort le masque pour que la pièce qui bloque la sangle se casse. (Problème de résistance mécanique) . <br/> <br/></commentaire>
</avis>
<avis>
<auteur>nicolas</auteur>
<note>4</note>
<point_positif>qualité prix</point_positif>
<point_negatif>reglage latéral peut étre un peu fragile (à voir)</point_negatif>
<date>03/10/2011</date>
<commentaire>plutôt satisfait de mon achat (pratique occasionnelle de plongée sans bouteille)</commentaire>
</avis>
<avis>
<auteur>frederic</auteur>
<note>4</note>
<point_positif>tres bon masque</point_positif>
<point_negatif>reglage de la sangle qui se deregle facilement</point_negatif>
<date>01/10/2011</date>
<commentaire>tres bon qualitee prix pour se masque <br/>seul defaut la sangle qui se deregle facilement</commentaire>
</avis>
<avis>
<auteur>thomas</auteur>
<note>4</note>
<point_positif>bon style - simple et esthétique à la fois</point_positif>
<point_negatif>buée ( problème classique )</point_negatif>
<date>30/09/2011</date>
<commentaire>la formule masque + tuba aurait été attractive</commentaire>
</avis>
<avis>
<auteur>Soiz</auteur>
<note>3</note>
<point_positif>colle bien au visage, bonne visibilité</point_positif>
<point_negatif>se dérègle souvent, les fixations ne tiennent pas</point_negatif>
<date>29/09/2011</date>
<commentaire>le masque est très bien. J'avais du mal à en trouver un qui ne me face pas mal au nez et celui la est très bien. Par contre, les fixations sur le coté ne tiennent pas du tout. En le mettant, le masque se dérègle... du coup il faut se débrouiller pour le régler quand il est placé sur le visage! Compliqué...</commentaire>
</avis>
<avis>
<auteur>Maurice</auteur>
<note>5</note>
<point_positif>CONFORTABLE ET EFFICACE</point_positif>
<point_negatif>DESIGN</point_negatif>
<date>28/09/2011</date>
<commentaire>Pour un prix correct, le produit répond parfaitement à une utilisation de loisir.</commentaire>
</avis>
</liste_avis>
<liste_avis>
<avis>
<auteur>François</auteur>
<note>3</note>
<point_positif>bonne souplesse et confort du silicone</point_positif>
<point_negatif>9 fois sur 10 la sangle se dérègle avant la plongé</point_negatif>
<date>01/01/2013</date>
<commentaire>le système de verrouillage de la sangle est tout à fait inefficace tant que le masque n'est pas sur le visage.<br/>ce qui oblige à re-règler le masque quasiment à chaque fois.</commentaire>
</avis>
<avis>
<auteur>Marc</auteur>
<note>4</note>
<point_positif>Faible encombrement, longévité de la jupe</point_positif>
<point_negatif>Boucles en plastique</point_negatif>
<date>23/12/2012</date>
<commentaire>Mon premier masque (il y a 10 ans) :) Un produit intéressant mais deux points à sérieusement prendre en compte :<br/>- masque pour les visages fins (bien pour les enfants) : sinon pas adapté du tout<br/>- boucles en plastique (qui permettent d'accrocher la sangle) cassable et (presque) introuvable : c'est cheap par rapport aux concurrents<br/><br/>Aujourd'hui, 'ai grandi, j'ai un Mares avec des boucles plus solides (mais à 40 euros...). En synthèse, un bon modèle pour commencer en occasionnel</commentaire>
</avis>
<avis>
<auteur>Marc</auteur>
<note>1</note>
<point_positif>Design</point_positif>
<point_negatif>Buée - pas étanche - attache mauvaise qualite</point_negatif>
<date>05/06/2012</date>
<commentaire>J'ai utilisé ce masque 2 fois et j'en suis très déçu. L'eau rentre rapidement à l'intérieur et quand on essaye de mieux serrer les attaches celles ci se détendent automatiquement... Ne parlons pas de la buée toutes les 30 secondes il faut nettoyer le verre. Bref je suis déçu et je ne le recommande pas même à ce niveau de prix.</commentaire>
</avis>
<avis>
<auteur>Lorane</auteur>
<note>4</note>
<point_positif>esthétique, pas de buée</point_positif>
<point_negatif>système de réglage fragile</point_negatif>
<date>07/05/2012</date>
<commentaire>le masque se dérègle trop facilement.<br/></commentaire>
</avis>
<avis>
<auteur>m</auteur>
<note>3</note>
<point_positif>Bonne visibilité et confort.</point_positif>
<point_negatif>Système de serrage fragile !</point_negatif>
<date>04/10/2011</date>
<commentaire>Très bonne visibilité. Absence de condensation dans les verres. Absence de fuite. Confortable sur le visage. Mais système de serrage fragile ! Il a sufis que je serre un peut fort le masque pour que la pièce qui bloque la sangle se casse. (Problème de résistance mécanique) . <br/> <br/></commentaire>
</avis>
<avis>
<auteur>nicolas</auteur>
<note>4</note>
<point_positif>qualité prix</point_positif>
<point_negatif>reglage latéral peut étre un peu fragile (à voir)</point_negatif>
<date>03/10/2011</date>
<commentaire>plutôt satisfait de mon achat (pratique occasionnelle de plongée sans bouteille)</commentaire>
</avis>
<avis>
<auteur>frederic</auteur>
<note>4</note>
<point_positif>tres bon masque</point_positif>
<point_negatif>reglage de la sangle qui se deregle facilement</point_negatif>
<date>01/10/2011</date>
<commentaire>tres bon qualitee prix pour se masque <br/>seul defaut la sangle qui se deregle facilement</commentaire>
</avis>
<avis>
<auteur>thomas</auteur>
<note>4</note>
<point_positif>bon style - simple et esthétique à la fois</point_positif>
<point_negatif>buée ( problème classique )</point_negatif>
<date>30/09/2011</date>
<commentaire>la formule masque + tuba aurait été attractive</commentaire>
</avis>
<avis>
<auteur>Soiz</auteur>
<note>3</note>
<point_positif>colle bien au visage, bonne visibilité</point_positif>
<point_negatif>se dérègle souvent, les fixations ne tiennent pas</point_negatif>
<date>29/09/2011</date>
<commentaire>le masque est très bien. J'avais du mal à en trouver un qui ne me face pas mal au nez et celui la est très bien. Par contre, les fixations sur le coté ne tiennent pas du tout. En le mettant, le masque se dérègle... du coup il faut se débrouiller pour le régler quand il est placé sur le visage! Compliqué...</commentaire>
</avis>
<avis>
<auteur>Maurice</auteur>
<note>5</note>
<point_positif>CONFORTABLE ET EFFICACE</point_positif>
<point_negatif>DESIGN</point_negatif>
<date>28/09/2011</date>
<commentaire>Pour un prix correct, le produit répond parfaitement à une utilisation de loisir.</commentaire>
</avis>
</liste_avis>
