<liste_avis>
<avis>
<auteur>Lara</auteur>
<note>4</note>
<point_positif>Facilite utilisation la couleur</point_positif>
<point_negatif>Aucun</point_negatif>
<date>05/12/2010</date>
<commentaire>Pour les enfant avec cheveux long c l idéal</commentaire>
</avis>
<avis>
<auteur>Stéphanie</auteur>
<note>5</note>
<point_positif>Evite le tiraillement des cheveux par la sangle</point_positif>
<point_negatif>Aucun</point_negatif>
<date>02/12/2010</date>
<commentaire>Produit très pratique et confortable.<br/>Mon enfant de 4 ans pouvait le mettre et l'enlever sans s'arracher les cheveux.</commentaire>
</avis>
<avis>
<auteur>François</auteur>
<note>5</note>
<point_positif>Son design</point_positif>
<point_negatif>Aucun</point_negatif>
<date>28/10/2010</date>
<commentaire>Enfin les sangles ne se tortillent plus dans les cheveux.</commentaire>
</avis>
<avis>
<auteur>Dominique</auteur>
<note>4</note>
<point_positif>Doux, motifs et couleurs originaux</point_positif>
<point_negatif>aucun</point_negatif>
<date>04/10/2010</date>
<commentaire>Trés bon article, de qualité, travail soigneux, à recommander</commentaire>
</avis>
<avis>
<auteur>oxygène33</auteur>
<note>4</note>
<point_positif>Evite la sangle de faire mal, pratique à installer</point_positif>
<point_negatif>RAS</point_negatif>
<date>16/07/2010</date>
<commentaire>Bonne tenue.</commentaire>
</avis>
<avis>
<auteur>Jacky</auteur>
<note>4</note>
<point_positif>pas de problem</point_positif>
<point_negatif>rien</point_negatif>
<date>15/07/2010</date>
<commentaire>Je suis très content</commentaire>
</avis>
</liste_avis>
<liste_avis>
<avis>
<auteur>Lara</auteur>
<note>4</note>
<point_positif>Facilite utilisation la couleur</point_positif>
<point_negatif>Aucun</point_negatif>
<date>05/12/2010</date>
<commentaire>Pour les enfant avec cheveux long c l idéal</commentaire>
</avis>
<avis>
<auteur>Stéphanie</auteur>
<note>5</note>
<point_positif>Evite le tiraillement des cheveux par la sangle</point_positif>
<point_negatif>Aucun</point_negatif>
<date>02/12/2010</date>
<commentaire>Produit très pratique et confortable.<br/>Mon enfant de 4 ans pouvait le mettre et l'enlever sans s'arracher les cheveux.</commentaire>
</avis>
<avis>
<auteur>François</auteur>
<note>5</note>
<point_positif>Son design</point_positif>
<point_negatif>Aucun</point_negatif>
<date>28/10/2010</date>
<commentaire>Enfin les sangles ne se tortillent plus dans les cheveux.</commentaire>
</avis>
<avis>
<auteur>Dominique</auteur>
<note>4</note>
<point_positif>Doux, motifs et couleurs originaux</point_positif>
<point_negatif>aucun</point_negatif>
<date>04/10/2010</date>
<commentaire>Trés bon article, de qualité, travail soigneux, à recommander</commentaire>
</avis>
<avis>
<auteur>oxygène33</auteur>
<note>4</note>
<point_positif>Evite la sangle de faire mal, pratique à installer</point_positif>
<point_negatif>RAS</point_negatif>
<date>16/07/2010</date>
<commentaire>Bonne tenue.</commentaire>
</avis>
<avis>
<auteur>Jacky</auteur>
<note>4</note>
<point_positif>pas de problem</point_positif>
<point_negatif>rien</point_negatif>
<date>15/07/2010</date>
<commentaire>Je suis très content</commentaire>
</avis>
</liste_avis>
