<liste_avis>
<avis>
<auteur>Flo</auteur>
<note>3</note>
<point_positif>Faciliter à se la procurer</point_positif>
<point_negatif>Valve de gonflage</point_negatif>
<date>28/06/2011</date>
<commentaire>J'ai acheté ce produit pour avoir des chambres à air de secours pour la poucette 3 roues de mon fils (18 mois). Je n'ai pas encore eu l'occasion de m'en servir. Je regrette de na pas avoir fait attention au type de valve, j'ai donc été obligé de racheter un embout de pompe à vélo.</commentaire>
</avis>
<avis>
<auteur>arnaud</auteur>
<note>5</note>
<point_positif>mise en place simple</point_positif>
<point_negatif>ras</point_negatif>
<date>27/06/2011</date>
<commentaire>ras</commentaire>
</avis>
<avis>
<auteur>Bruno</auteur>
<note>4</note>
<point_positif>faicle pour le montage</point_positif>
<point_negatif>néant</point_negatif>
<date>27/06/2011</date>
<commentaire>bon produit</commentaire>
</avis>
<avis>
<auteur>dubreuil</auteur>
<note>4</note>
<point_positif>très facile à monter</point_positif>
<point_negatif>rien à dire</point_negatif>
<date>31/05/2011</date>
<commentaire>un bon rapport qualité/prix</commentaire>
</avis>
<avis>
<auteur>Christophe</auteur>
<note>4</note>
<point_positif>Rapport Qualité / Prix, résistance à la creuvaison</point_positif>
<point_negatif>poreuse assez rapidement</point_negatif>
<date>30/05/2011</date>
<commentaire>Utilisée sur des roues de poussette. Dommage qu'elles n'existent pas avec une valve légèrement plus longue.</commentaire>
</avis>
<avis>
<auteur>Laurent</auteur>
<note>5</note>
<point_positif>Idéal pour les poussettes "Red Castle" aussi !!!</point_positif>
<point_negatif>Aucun</point_negatif>
<date>13/08/2010</date>
<commentaire>En stock dans tous les magasins Décathlon et beaucoup moins cher qu'en magasin "spécialisés".</commentaire>
</avis>
<avis>
<auteur>ALAIN</auteur>
<note>4</note>
<point_positif>packaging  un point de vue positif sur le produit</point_positif>
<point_negatif>rien de spécifique à signaler</point_negatif>
<date>23/07/2010</date>
<commentaire>utilise ce produit pour le b'twin , produit fiable, facile d'utilisation en ce qui concerne le montage et d'utilisaton courante(gonflage,échange).</commentaire>
</avis>
<avis>
<auteur>Laurent</auteur>
<note>4</note>
<point_positif>aucun</point_positif>
<point_negatif>petit bémol pour le prix</point_negatif>
<date>15/07/2010</date>
<commentaire>Le prix est dans la moyenne, quoique presque aussi cher qu'un 19 pouces mais bon, le temps de fabrication est le même; pour la tenue , à voir à l'usage et avec le temps...</commentaire>
</avis>
</liste_avis>
