<liste_avis>
<avis>
<auteur>valerie</auteur>
<note>4</note>
<point_positif>la position de l'enfant ,le confort</point_positif>
<point_negatif>la lumière avant pas assez résistante aux chutes</point_negatif>
<date>08/12/2012</date>
<commentaire>joli design et bonne ergonomie</commentaire>
</avis>
<avis>
<auteur>stephane</auteur>
<note>4</note>
<point_positif>beau,impeccable pour les filles</point_positif>
<point_negatif>garde-boue arriere un peu fragile,car long</point_negatif>
<date>30/08/2012</date>
<commentaire>Très beau vélo,très bien pour une fille de 7 ans, bonne qualité, le garde boue arrière est très exposé car tenu par des petites barres, autrement pas de soucis particulieres</commentaire>
</avis>
</liste_avis>
