<liste_avis>
<avis>
<auteur>noel</auteur>
<note>5</note>
<point_positif>parfait</point_positif>
<point_negatif>rien</point_negatif>
<date>13/01/2013</date>
<commentaire>j'en suis contant il n'y a rien à signaler , ça tien bien , les mains respire bien c'est jolie et très confortable à porter .<br/>je suis satisfait de mon achat .</commentaire>
</avis>
<avis>
<auteur>Xavier</auteur>
<note>4</note>
<point_positif>Protège efficacement en cas de chute !</point_positif>
<point_negatif>Prévoir une taille au-dessus lors de l'achat.</point_negatif>
<date>23/12/2012</date>
<commentaire>Aucun regret jusque là, ils sont confortables et résistants. Protègent du froid et surtout des chutes. J'ai même une paire supplémentaire pour le <a class="noUrlStyle" href="/Acheter/golf">golf</a> !!! C'est sérieux.</commentaire>
</avis>
<avis>
<auteur>Laurent</auteur>
<note>4</note>
<point_positif>l'ensemble du gant est très solide</point_positif>
<point_negatif>aucun</point_negatif>
<date>27/11/2012</date>
<commentaire>c'est ma troisième paire en quelques années, ils sont très solide bien que la dernière génération l'était encore plus.</commentaire>
</avis>
<avis>
<auteur>ren</auteur>
<note>2</note>
<point_positif>renfort</point_positif>
<point_negatif>les coutures</point_negatif>
<date>04/11/2012</date>
<commentaire>A eviter apres 3 sorties les coutures se defond deja....</commentaire>
</avis>
<avis>
<auteur>Pascal</auteur>
<note>3</note>
<point_positif>Confort, légèreté</point_positif>
<point_negatif>Difficiles à enfiler</point_negatif>
<date>22/10/2012</date>
<commentaire>Sur ce site, l'assistant taille me conseille "L" pour un tour de main de 22cm. <br/>À la réception des gants, la taille indiquée sur l'étiquette est 19,4-19,9 cm pour une taille "L" et 20-20,5 cm pour une taille "XL".<br/>Donc, a priori une déception, cependant, une fois que le gant est enfilé ( assez difficilement ), on se retrouve à l'aise, la longueur des doigts correspond. <br/>Dans une autre partie du site, il y a un autre assistant, qui indique d'autres tailles</commentaire>
</avis>
<avis>
<auteur>Benjamin</auteur>
<note>4</note>
<point_positif>Souple, robuste, agréable à porter, confortable</point_positif>
<point_negatif>Pas encore constaté</point_negatif>
<date>01/08/2012</date>
<commentaire>De bon gant pour la pratique du VTT en été. <br/><br/>Je les utilise à chacune de mes sorties, ils procurent un bon amorti des vibrations du guidon et ont une bonne capacité d'accroche.<br/><br/>De plus en cas de chute ils protègent bien la paume des mains sans s’abîmer (robustes).<br/></commentaire>
</avis>
<avis>
<auteur>Régis</auteur>
<note>4</note>
<point_positif>confort maniable</point_positif>
<point_negatif>ras</point_negatif>
<date>08/07/2012</date>
<commentaire>no comment</commentaire>
</avis>
<avis>
<auteur>andre</auteur>
<note>4</note>
<point_positif>facile a mettre</point_positif>
<point_negatif>usure prematuré au niveau des renfort</point_negatif>
<date>03/07/2012</date>
<commentaire>bon gants.</commentaire>
</avis>
<avis>
<auteur>manuel</auteur>
<note>4</note>
<point_positif>couvrants et suffisamment aérés</point_positif>
<point_negatif>nope</point_negatif>
<date>30/06/2012</date>
<commentaire>bon produit</commentaire>
</avis>
<avis>
<auteur>boulogne</auteur>
<note>4</note>
<point_positif>gants super meme avec ces chaleurs</point_positif>
<point_negatif>doitgs ont tendances  a tourner</point_negatif>
<date>29/06/2012</date>
<commentaire>continues a faire de supers  produits a de tres bons prix comme on dit  vive le sport</commentaire>
</avis>
</liste_avis>
