<liste_avis>
<avis>
<auteur>Pierre</auteur>
<note>3</note>
<point_positif>couleur, pratique, accroche par le bouchon</point_positif>
<point_negatif>mauvaise étanchéité</point_negatif>
<date>24/06/2012</date>
<commentaire>Bien concue, la taille est très pratique, elle peut être accroché par le bouchon. Elle semble étanche quand on la penche ou la retourne mais on se retrouve avec le sac plein d'eau quand on l'utilise en randonnée. Si l'ouverture du goulot était plus grande on pourait l'utiliser comme contenant pour des objets.</commentaire>
</avis>
<avis>
<auteur>Gregory</auteur>
<note>4</note>
<point_positif>léger,bonne étancheité.</point_positif>
<point_negatif>la colle de l'étiquette</point_negatif>
<date>15/06/2012</date>
<commentaire>super produit ( qui se rapproche des produit Na...ne) du coup un goulot plus large et un peu plus de capacité eut été mieux.Mais rapport qualité prix y a rien à dire....comme souvent avec vos produits.<br/>Par contre, comme déjà dit par un autre utilisateur, enlever l'étiquette relève du parcours du combattant.Même avec des produits type dissolvant ou W40 ça laisse une vilaine trace opaque et blanchâtre sur la gourde.C'est pas bien grave mais sur le coup ...ça énerve un peu.</commentaire>
</avis>
<avis>
<auteur>Dot</auteur>
<note>1</note>
<point_positif>Couleurs et forme sympas</point_positif>
<point_negatif>L'étiquette ++++</point_negatif>
<date>31/05/2012</date>
<commentaire>Une énorme étiquette laissant une trace de colle coriace. La gourde reste toute collante. Je l'ai jetée...<br/>Conseils aux utilisateurs : mieux vaut encore laisser l'étiquette en place...</commentaire>
</avis>
<avis>
<auteur>Manu</auteur>
<note>5</note>
<point_positif>Bonne couleurs, légère, robuste</point_positif>
<point_negatif>/</point_negatif>
<date>29/04/2012</date>
<commentaire>Bon produit en general...<br/>Une idée pour le product manager; créer aussi une modele avec les mêmes caracteristiques mais plus petit pour les enfants...</commentaire>
</avis>
</liste_avis>
