<liste_avis>
<avis>
<auteur>Isabelle</auteur>
<note>3</note>
<point_positif>Légèreté</point_positif>
<point_negatif>Coutures trop justes, gants décousus 1ère mise</point_negatif>
<date>16/01/2013</date>
<commentaire>A trop rogner sur la qualité de fabrication, on n'obtient rien d'excellent !</commentaire>
</avis>
<avis>
<auteur>Emmanuel</auteur>
<note>4</note>
<point_positif>léger mais assez efficace</point_positif>
<point_negatif>reste limité comme protection</point_negatif>
<date>12/12/2012</date>
<commentaire>Bon rapport qualité prix</commentaire>
</avis>
<avis>
<auteur>ines noelle</auteur>
<note>4</note>
<point_positif>très imperméabilisant et chaud</point_positif>
<point_negatif>monte pas assez haut aux poignees</point_negatif>
<date>09/12/2012</date>
<commentaire>rien</commentaire>
</avis>
<avis>
<auteur>Christophe</auteur>
<note>5</note>
<point_positif>Imperméable et chauds</point_positif>
<point_negatif>Inutilisable avec un smatphone</point_negatif>
<date>07/12/2012</date>
<commentaire>Très satisfait de cette paire de gants,</commentaire>
</avis>
<avis>
<auteur>didier</auteur>
<note>5</note>
<point_positif>coupe et du frod</point_positif>
<point_negatif>rien</point_negatif>
<date>07/12/2012</date>
<commentaire>r a s</commentaire>
</avis>
<avis>
<auteur>christophe</auteur>
<note>5</note>
<point_positif>isolant, très chaud,</point_positif>
<point_negatif>néant</point_negatif>
<date>07/12/2012</date>
<commentaire>à conseiller et surtout à acheter c'est le bon moment</commentaire>
</avis>
<avis>
<auteur>Laetitia</auteur>
<note>4</note>
<point_positif>chaud et coupe vent</point_positif>
<point_negatif>esthétique moyenne.</point_negatif>
<date>03/12/2012</date>
<commentaire>Bien pour une utilisation type sortie sur sentiers de promenade par temps frais et en saison froide. Protège bien du froid et du vent. Léger. <br/>Esthétique moyenne pour une utilisation en ville.</commentaire>
</avis>
</liste_avis>
