<liste_avis>
<avis>
<auteur>CEDRIC</auteur>
<note>5</note>
<point_positif>qualité/prix</point_positif>
<point_negatif>RAS</point_negatif>
<date>31/05/2012</date>
<commentaire>Bravo pour ce produit, top qualité et pas cher. Ma fille de 18 mois le porte à merveille.Il est très robuste et très agréable.<br/>Bravo pour le prix ! (en comparaison avec ce qu'on achète d'habitude chez okaidi)<br/>A quand de nouvelle couleur ?</commentaire>
</avis>
<avis>
<auteur>Sebastien</auteur>
<note>5</note>
<point_positif>modularité, confort, prix</point_positif>
<point_negatif>N/A</point_negatif>
<date>24/04/2012</date>
<commentaire>Franchement bien. Dommage qu'il n'y ait pas le choix avec le même produit fabriqué en France.</commentaire>
</avis>
<avis>
<auteur>gladys</auteur>
<note>4</note>
<point_positif>Fonctionnel, confortable, taille réglable</point_positif>
<point_negatif>peu de choix de couleurs, se froisse facilement</point_negatif>
<date>23/04/2012</date>
<commentaire>Pantalon double emploi : pour sortir ou pour faire du sport<br/>Facile à entretenir<br/>Confortable + taille réglable<br/>Fonctionnel : plusieurs poches</commentaire>
</avis>
<avis>
<auteur>nine</auteur>
<note>5</note>
<point_positif>une super coupe et super matiere</point_positif>
<point_negatif>pas tres fashion pour un ado</point_negatif>
<date>24/11/2011</date>
<commentaire>ce pantalon acheté par hasard et en urgence pour 2 de mes enfants s'avere etre une excellente acquisition</commentaire>
</avis>
<avis>
<auteur>Diane</auteur>
<note>4</note>
<point_positif>Pratique, résistant</point_positif>
<point_negatif>Couleur devient progressivement "vintage"</point_negatif>
<date>23/11/2011</date>
<commentaire>Mon fils a apprécié les poches, l'enfilage rapide pas fragile, et moi, pas de repassage !!!<br/>NB Il fait de l'escalade avec.</commentaire>
</avis>
<avis>
<auteur>Jean-Louis</auteur>
<note>4</note>
<point_positif>original, facile à porter</point_positif>
<point_negatif>pas de taille intermédiaire</point_negatif>
<date>22/11/2011</date>
<commentaire>plus de taille: mon garçon est entre 2 et pas beaucoup de choix. Vetement d'aventurier (plein de poches) idéal pour les enfants.</commentaire>
</avis>
<avis>
<auteur>fabry</auteur>
<note>4</note>
<point_positif>matiere agreable</point_positif>
<point_negatif>aucun</point_negatif>
<date>28/09/2011</date>
<commentaire>le pantalon est agreable à porter,souple et bien taillé. Dommage qu'il  n'y est pas plus de couleur au choix</commentaire>
</avis>
<avis>
<auteur>catherine</auteur>
<note>4</note>
<point_positif>elegant</point_positif>
<point_negatif>pas pour le moment</point_negatif>
<date>28/09/2011</date>
<commentaire>satisfait</commentaire>
</avis>
<avis>
<auteur>Véronique</auteur>
<note>4</note>
<point_positif>Pratique (long ou court), peu salissant, vite sec</point_positif>
<point_negatif>un peu étroit en taille (1 taille de plus)</point_negatif>
<date>10/09/2011</date>
<commentaire>Super pour mon ado: nous sommes allés 2 sem en Grèce, adapté à la ville, à la campagne, pas chaud, facile à nettoyer, se marie en coloris avec tout</commentaire>
</avis>
<avis>
<auteur>Guillaume</auteur>
<note>4</note>
<point_positif>-séche vite,se nettoie facilement,convertible etc.</point_positif>
<point_negatif>-bouton pression qui ne clipse pas très bien.</point_negatif>
<date>31/08/2011</date>
<commentaire>J'ai utilisé ce pantalon pour un trek de 10 jours,en partie sous de fortes pluies où il m'a donné entière satisfaction(j'ai eu les jambes à peine mouillées).Il sèche extrêmement vite: il suffisait d'une dizaine de minutes pour qu'il soit sec dans le refuge ou même d'une éclaircie pendant la marche pour qu'il commence à sécher.Il est aussi très pratique puisque que l'on peut le convertir en bermuda s'il fait plus chaud.<br/>Je recommande chaudement ce produit.</commentaire>
</avis>
</liste_avis>
