<liste_avis>
<avis>
<auteur>Pistache</auteur>
<note>5</note>
<point_positif>Bien coupé</point_positif>
<point_negatif>Les boutons de la ceinture</point_negatif>
<date>14/01/2013</date>
<commentaire>Idéal, sauf les deux petits boutons de la ceinture difficile à enfiler, sur l'ancienne version de ce pantalon, l'unique boutons permettait une attache rapide et fiable.<br/>Ici, on met un peu plus de temps surtout si les doigts sont engourdis par le froid.<br/>Dommage</commentaire>
</avis>
<avis>
<auteur>Marie-Pierre</auteur>
<note>3</note>
<point_positif>Pratique, confortable, sèche vite</point_positif>
<point_negatif>Couleur et coutures fragiles</point_negatif>
<date>19/11/2012</date>
<commentaire>Le pantalon est pratique et confortable en randonnée, il sèche très vite.<br/>En revanche, après le premier lavage, le soir même de la randonnée, la couleur est passée à l'endroit où il y avait des taches de boue et l'empiècement de la ceinture, cousu certainement trop à ras du tissus, est ressorti de la machine à laver décousu sur 1,5 cm.</commentaire>
</avis>
<avis>
<auteur>anne</auteur>
<note>4</note>
<point_positif>leger et matiere agreable</point_positif>
<point_negatif>serait bien avec taille reglable (velcro par exemp</point_negatif>
<date>23/08/2012</date>
<commentaire>ras</commentaire>
</avis>
<avis>
<auteur>Cécile</auteur>
<note>5</note>
<point_positif>confortable, sèchage rapide</point_positif>
<point_negatif>pas assez de poches avec fermeture éclair</point_negatif>
<date>13/07/2012</date>
<commentaire>le bas du pantalon n'est pas pratique à enlever sans enlever ses chaussures de randonnée</commentaire>
</avis>
<avis>
<auteur>brochot</auteur>
<note>4</note>
<point_positif>la modulation short pantalon</point_positif>
<point_negatif>la tenue de la couleur au lavage</point_negatif>
<date>09/07/2012</date>
<commentaire>.</commentaire>
</avis>
<avis>
<auteur>Pierre</auteur>
<note>4</note>
<point_positif>très léger</point_positif>
<point_negatif>rien</point_negatif>
<date>08/07/2012</date>
<commentaire>bon achat</commentaire>
</avis>
<avis>
<auteur>cécile</auteur>
<note>4</note>
<point_positif>matière = coton bio</point_positif>
<point_negatif>transformation en short au lieu de pantacourt</point_negatif>
<date>07/07/2012</date>
<commentaire>Voilà un pantalon de rando confortable mais que l'on ne peut porter en mi-saison , soit trop chaud en pantalon soit trop frais en short , j'aurais préféré une transformation en pantacourt .<br/>entretien facile , sechage assez rapide .</commentaire>
</avis>
<avis>
<auteur>nathalie</auteur>
<note>5</note>
<point_positif>modulable, confortable,pratique...</point_positif>
<point_negatif>aucun</point_negatif>
<date>07/07/2012</date>
<commentaire>Les jambes s'enlevent et se mettent trés facilememt.</commentaire>
</avis>
<avis>
<auteur>JANY</auteur>
<note>5</note>
<point_positif>TOUT, LE 2 EN 1 POUR 1 BON PRIX</point_positif>
<point_negatif>RIEN</point_negatif>
<date>03/07/2012</date>
<commentaire>UTILISE AU QUOTIDIEN,LEGER,NE BOUGE PAS AU LAVAGE</commentaire>
</avis>
<avis>
<auteur>betty</auteur>
<note>4</note>
<point_positif>confortable et bien coupé</point_positif>
<point_negatif>aucun</point_negatif>
<date>02/07/2012</date>
<commentaire>très bon achat, pas encore testé en short, mais le pantalon me convient très bien</commentaire>
</avis>
</liste_avis>
