<liste_avis>
<avis>
<auteur>jacky</auteur>
<note>5</note>
<point_positif>palourdes</point_positif>
<point_negatif>ras</point_negatif>
<date>28/11/2012</date>
<commentaire>produit conforme pour la peche a pied</commentaire>
</avis>
<avis>
<auteur>Olivier</auteur>
<note>5</note>
<point_positif>pratique, solide</point_positif>
<point_negatif>très cher !!!</point_negatif>
<date>08/09/2012</date>
<commentaire>un prix plus bas rendrait plus populaire la pêche à pieds, ce n'est pas un produit très élaboré...</commentaire>
</avis>
</liste_avis>
