<liste_avis>
<avis>
<auteur>Nomada</auteur>
<note>4</note>
<point_positif>Jolie coupe / confort / favorise la silouette</point_positif>
<point_negatif>Un peu trop courte quand on est grande...</point_negatif>
<date>25/09/2012</date>
<commentaire>Jupe très bien coupée, on est à l'aise pour bouger, matière agéable. Seul bémol : la longueur...je mesure 1,72 et du coup la jupe est un peu trop courte...</commentaire>
</avis>
<avis>
<auteur>sylvie</auteur>
<note>5</note>
<point_positif>le petit plissé qui rend la jupe moins stricte</point_positif>
<point_negatif>une seule couleur</point_negatif>
<date>05/09/2012</date>
<commentaire>tres agréable a porter , seche vite</commentaire>
</avis>
<avis>
<auteur>Anne</auteur>
<note>5</note>
<point_positif>facilité d'entretien, jolie coupe élégante</point_positif>
<point_negatif>taille petit</point_negatif>
<date>05/09/2012</date>
<commentaire>Enchantée par cet article à prix raisonnable !</commentaire>
</avis>
<avis>
<auteur>beatrice</auteur>
<note>4</note>
<point_positif>la liseré blanc les petits plis sa forme</point_positif>
<point_negatif>rien</point_negatif>
<date>02/09/2012</date>
<commentaire>je prends cette jupe short pour courir car je cherchais un modèle sympa féminin et pas trop cher (il y a juste les poches étant donné qu'elles sont faites pour le tennis elles ne servent à rien) mais cet ensemble est agréable à porter et féminin</commentaire>
</avis>
<avis>
<auteur>Tennis</auteur>
<note>5</note>
<point_positif>legere et jolie</point_positif>
<point_negatif>non</point_negatif>
<date>10/07/2012</date>
<commentaire>Excellent pour jouer.</commentaire>
</avis>
<avis>
<auteur>Déborah</auteur>
<note>5</note>
<point_positif>Legere, confortable</point_positif>
<point_negatif>Aucun</point_negatif>
<date>06/07/2012</date>
<commentaire>Bon rapport qualité prix<br/>Poches pratique</commentaire>
</avis>
<avis>
<auteur>sylvie</auteur>
<note>4</note>
<point_positif>coupe, couleur et matière</point_positif>
<point_negatif>pas forcément pratique pour la balle</point_negatif>
<date>05/07/2012</date>
<commentaire>.</commentaire>
</avis>
<avis>
<auteur>ANNE</auteur>
<note>5</note>
<point_positif>matière agréable a porter, facile d'entretien,</point_positif>
<point_negatif>pas de probleme</point_negatif>
<date>02/07/2012</date>
<commentaire>Très bon rapport qlt/prix</commentaire>
</avis>
<avis>
<auteur>Manon</auteur>
<note>5</note>
<point_positif>Emplacement pour les balles</point_positif>
<point_negatif>aucun</point_negatif>
<date>02/07/2012</date>
<commentaire>Très agréable à porter, très féminin</commentaire>
</avis>
<avis>
<auteur>ANNE SOPHIE</auteur>
<note>4</note>
<point_positif>légère</point_positif>
<point_negatif>poche de balles pas pratique</point_negatif>
<date>30/06/2012</date>
<commentaire>Changer le systeme de poche</commentaire>
</avis>
</liste_avis>
<liste_avis>
<avis>
<auteur>Nomada</auteur>
<note>4</note>
<point_positif>Jolie coupe / confort / favorise la silouette</point_positif>
<point_negatif>Un peu trop courte quand on est grande...</point_negatif>
<date>25/09/2012</date>
<commentaire>Jupe très bien coupée, on est à l'aise pour bouger, matière agéable. Seul bémol : la longueur...je mesure 1,72 et du coup la jupe est un peu trop courte...</commentaire>
</avis>
<avis>
<auteur>sylvie</auteur>
<note>5</note>
<point_positif>le petit plissé qui rend la jupe moins stricte</point_positif>
<point_negatif>une seule couleur</point_negatif>
<date>05/09/2012</date>
<commentaire>tres agréable a porter , seche vite</commentaire>
</avis>
<avis>
<auteur>Anne</auteur>
<note>5</note>
<point_positif>facilité d'entretien, jolie coupe élégante</point_positif>
<point_negatif>taille petit</point_negatif>
<date>05/09/2012</date>
<commentaire>Enchantée par cet article à prix raisonnable !</commentaire>
</avis>
<avis>
<auteur>beatrice</auteur>
<note>4</note>
<point_positif>la liseré blanc les petits plis sa forme</point_positif>
<point_negatif>rien</point_negatif>
<date>02/09/2012</date>
<commentaire>je prends cette jupe short pour courir car je cherchais un modèle sympa féminin et pas trop cher (il y a juste les poches étant donné qu'elles sont faites pour le tennis elles ne servent à rien) mais cet ensemble est agréable à porter et féminin</commentaire>
</avis>
<avis>
<auteur>Tennis</auteur>
<note>5</note>
<point_positif>legere et jolie</point_positif>
<point_negatif>non</point_negatif>
<date>10/07/2012</date>
<commentaire>Excellent pour jouer.</commentaire>
</avis>
<avis>
<auteur>Déborah</auteur>
<note>5</note>
<point_positif>Legere, confortable</point_positif>
<point_negatif>Aucun</point_negatif>
<date>06/07/2012</date>
<commentaire>Bon rapport qualité prix<br/>Poches pratique</commentaire>
</avis>
<avis>
<auteur>sylvie</auteur>
<note>4</note>
<point_positif>coupe, couleur et matière</point_positif>
<point_negatif>pas forcément pratique pour la balle</point_negatif>
<date>05/07/2012</date>
<commentaire>.</commentaire>
</avis>
<avis>
<auteur>ANNE</auteur>
<note>5</note>
<point_positif>matière agréable a porter, facile d'entretien,</point_positif>
<point_negatif>pas de probleme</point_negatif>
<date>02/07/2012</date>
<commentaire>Très bon rapport qlt/prix</commentaire>
</avis>
<avis>
<auteur>Manon</auteur>
<note>5</note>
<point_positif>Emplacement pour les balles</point_positif>
<point_negatif>aucun</point_negatif>
<date>02/07/2012</date>
<commentaire>Très agréable à porter, très féminin</commentaire>
</avis>
<avis>
<auteur>ANNE SOPHIE</auteur>
<note>4</note>
<point_positif>légère</point_positif>
<point_negatif>poche de balles pas pratique</point_negatif>
<date>30/06/2012</date>
<commentaire>Changer le systeme de poche</commentaire>
</avis>
</liste_avis>
