<liste_avis>
<avis>
<auteur>alex</auteur>
<note>3</note>
<point_positif>look assorti au skis enduro LX 800 black</point_positif>
<point_negatif>la peinture noir ne va pas rester longtemps</point_negatif>
<date>05/01/2013</date>
<commentaire>acheté en décembre 2012 : bon look et assorti aux skis salomon enduro LX 800. Les poignées sont agréables, ils sont légers et robustes. Le seul vrai soucis c'est la peinture noir. Au moindre choc la peinture s'en va pour laisser place à de magnifiques rayures.<br/>Attention toutefois au vendeur pour vous donner la bonne taille de bâtons : ils n'ont pas toutes les tailles en stock et sont prêts à vous vendre une mauvaise taille (10cm de moins) en vous assurant que c'est la taille qu'il vous faut !!!</commentaire>
</avis>
</liste_avis>
