<liste_avis>
<avis>
<auteur>Charlotte</auteur>
<note>4</note>
<point_positif>frontal, taille</point_positif>
<point_negatif>couleur, souplesse</point_negatif>
<date>06/01/2013</date>
<commentaire>Le filet avec ce frontal en forme de vague et super jolie et vas parfaitement aux juments ! <br/>La taille est bien, il vas a ma jument et aux poneys de 1m45 environ. Mais, il faudrait d' autre couleurs comme marron.<br/>Ça fait déjà 4mois que j' utilise ce filet sur ma jument et il n' est pas encore souple? Même si je le graisse sauvant, il est encore très  " dur " .<br/><br/>Sinon, il est très jolie. :) <br/></commentaire>
</avis>
<avis>
<auteur>Fatiha</auteur>
<note>5</note>
<point_positif>cuir souple filet résistant</point_positif>
<point_negatif>rien</point_negatif>
<date>31/10/2012</date>
<commentaire>ce filet est génial il a un frontal trop beau cuir souple est génial  il est très résistant est classe en plus il va très bien sur mon poney je le recommande .</commentaire>
</avis>
<avis>
<auteur>lidya</auteur>
<note>5</note>
<point_positif>tout</point_positif>
<point_negatif>dur au debut</point_negatif>
<date>05/10/2012</date>
<commentaire>Ce filet est très jolie et de très bon prix, le cuir une fois souple est génial et son frontal en vague strass est superbe je recommande beaucoup! Décathlon à fait un super choix de vendre ce filet ! j'adore !</commentaire>
</avis>
</liste_avis>
