<liste_avis>
<avis>
<auteur>Ulysse</auteur>
<note>4</note>
<point_positif>Goût</point_positif>
<point_negatif>Ouverture lorsqu'il fait chaud</point_negatif>
<date>24/08/2012</date>
<commentaire>Utilisé lors d'un trek au ladakh<br/>Le système d'ouverture est pratique mais quand il fait chaud et que ta barre est molle t'as intérêt à l'ouvrir à l'ancienne sinon c'est purée assurée. Niveau gout, ça vaut les grany. Il faudra penser à faire un équivalent du grany moelleux ! <br/></commentaire>
</avis>
<avis>
<auteur>G</auteur>
<note>4</note>
<point_positif>goût, format, prix</point_positif>
<point_negatif>rien</point_negatif>
<date>18/06/2012</date>
<commentaire>Le système clak est un pur gadget ne servant à rien (l'ouverture est facile par les zigzags de l'emballage).<br/>Hormis cela, la barre présente un gout agréable, peu sucré, chocolaté juste comme il faut... par contre pour avoir l'impression d'avoir mangé quelque chose, j'ai du en manger 3... peut etre le coté peu sucré donc peu calorique...</commentaire>
</avis>
<avis>
<auteur>David</auteur>
<note>4</note>
<point_positif>Texture, gout et ouverture</point_positif>
<point_negatif>Ouverture ;)</point_negatif>
<date>09/06/2012</date>
<commentaire>J'ai eu la chance d'etre testeur sur ce produit (et sur le sirop iso citron).<br/>Très bon produit, bon gout et bonne texture des nouvelles Clak.<br/>Les sytème d'ouverture est interessant car plus écologique (pas de perte de papier dans la nature, mais obligé de l'ouvrir avec les mains, avec les dents le truc c'est déchiré plusieurs fois ou alors je suis pas doué ;)</commentaire>
</avis>
<avis>
<auteur>Mark</auteur>
<note>5</note>
<point_positif>Facile à ouvrir et très bon</point_positif>
<point_negatif>Aucun</point_negatif>
<date>24/05/2012</date>
<commentaire>Très bonne marque de barres céréales.</commentaire>
</avis>
<avis>
<auteur>Jean-Pierre</auteur>
<note>5</note>
<point_positif>Ouverture facile, goût</point_positif>
<point_negatif>Rien</point_negatif>
<date>13/05/2012</date>
<commentaire>Testé hier lors d'un brevet de 200km, j'ai apprécié le goût, la facilité d'ouverture, cela m'a donné envie de goûter aux autres parfums de cette gamme.</commentaire>
</avis>
<avis>
<auteur>jeffrey</auteur>
<note>5</note>
<point_positif>gout</point_positif>
<point_negatif>aucun</point_negatif>
<date>24/04/2012</date>
<commentaire>J'adore ces barres, choco framboises, un delice.</commentaire>
</avis>
<avis>
<auteur>Anna</auteur>
<note>4</note>
<point_positif>peu de calories</point_positif>
<point_negatif>pas beaucoup de choco</point_negatif>
<date>29/12/2010</date>
<commentaire>pour le goûter ou pour des pauses à l'école</commentaire>
</avis>
<avis>
<auteur>ANTOINE</auteur>
<note>4</note>
<point_positif>goût</point_positif>
<point_negatif>resistance à la chaleur</point_negatif>
<date>20/05/2010</date>
<commentaire>trés apprécié de mes enfants !<br/>trop bon : il ne m'en reste plus pour le sport...</commentaire>
</avis>
<avis>
<auteur>FRANCOIS</auteur>
<note>3</note>
<point_positif>Coupe faim efficace</point_positif>
<point_negatif>Gout du chocolat</point_negatif>
<date>20/05/2010</date>
<commentaire>Un peu déçu par le gout du chocolat qui parait un peu "vieux".</commentaire>
</avis>
<avis>
<auteur>LAURENT</auteur>
<note>5</note>
<point_positif>agreable au gout et texture</point_positif>
<point_negatif>ras</point_negatif>
<date>17/05/2010</date>
<commentaire>en pleine effort un peu long a assimilé mais cette nouvelle recette & de loin meilleure a l'ancienne</commentaire>
</avis>
</liste_avis>
